undertone/__about__.py
undertone/__init__.py
undertone/core.py
undertone/event.py
undertone/key_names.py
undertone/screen.py
undertone/span.py
undertone/terminal.py
undertone-0.1.0.dist-info/METADATA
undertone-0.1.0.dist-info/WHEEL
undertone-0.1.0.dist-info/licenses/LICENSE
undertone-0.1.0.dist-info/RECORD
