Metadata-Version: 2.1
Name: undertone
Version: 0.1.0
Summary: A lightweight set of tools for interfacing with the terminal.
Project-URL: Documentation, https://github.com/unknown/undertone#readme
Project-URL: Issues, https://github.com/unknown/undertone/issues
Project-URL: Source, https://github.com/unknown/undertone
Author-email: bczsalba <bczsalba@gmail.com>
License-Expression: MIT
License-File: LICENSE
Classifier: Development Status :: 4 - Beta
Classifier: Programming Language :: Python :: 3.8
Classifier: Programming Language :: Python :: 3.9
Classifier: Programming Language :: Python :: 3.10
Classifier: Programming Language :: Python :: 3.11
Classifier: Programming Language :: Python :: Implementation :: CPython
Classifier: Programming Language :: Python :: Implementation :: PyPy
Requires-Python: >=3.8
